LICENSE
sssoon/__init__.py
sssoon/admin.py
sssoon/apps.py
sssoon/forms.py
sssoon/migrations/0001_initial.py
sssoon/migrations/0002_alter_mailinglist_id.py
sssoon/migrations/__init__.py
sssoon/models.py
sssoon/static/sssoon/css/bootstrap.css
sssoon/static/sssoon/css/bootstrap.css.map
sssoon/static/sssoon/css/bootstrap.min.css
sssoon/static/sssoon/css/custom.css
sssoon/static/sssoon/css/font-awesome.css
sssoon/static/sssoon/css/fonts/FontAwesome.otf
sssoon/static/sssoon/css/fonts/fontawesome-webfont.eot
sssoon/static/sssoon/css/fonts/fontawesome-webfont.svg
sssoon/static/sssoon/css/fonts/fontawesome-webfont.ttf
sssoon/static/sssoon/css/fonts/fontawesome-webfont.woff
sssoon/static/sssoon/css/formValidation.css
sssoon/static/sssoon/css/formValidation.min.css
sssoon/static/sssoon/css/style.default.css
sssoon/static/sssoon/fonts/glyphicons-halflings-regular.eot
sssoon/static/sssoon/fonts/glyphicons-halflings-regular.svg
sssoon/static/sssoon/fonts/glyphicons-halflings-regular.ttf
sssoon/static/sssoon/fonts/glyphicons-halflings-regular.woff
sssoon/static/sssoon/fonts/glyphicons-halflings-regular.woff2
sssoon/static/sssoon/img/paris.jpg
sssoon/static/sssoon/img/sprites/sprite.png
sssoon/static/sssoon/img/video-bg.jpg
sssoon/static/sssoon/js/bootstrap.min.js
sssoon/static/sssoon/js/formValidation.js
sssoon/static/sssoon/js/formValidation.min.js
sssoon/static/sssoon/js/formValidation.popular.js
sssoon/static/sssoon/js/formValidation.popular.min.js
sssoon/static/sssoon/js/framework/bootstrap.js
sssoon/static/sssoon/js/framework/bootstrap.min.js
sssoon/static/sssoon/js/framework/bootstrap4.js
sssoon/static/sssoon/js/framework/bootstrap4.min.js
sssoon/static/sssoon/js/framework/foundation.js
sssoon/static/sssoon/js/framework/foundation.min.js
sssoon/static/sssoon/js/framework/foundation5.js
sssoon/static/sssoon/js/framework/foundation5.min.js
sssoon/static/sssoon/js/framework/pure.js
sssoon/static/sssoon/js/framework/pure.min.js
sssoon/static/sssoon/js/framework/semantic.js
django_sssoon-0.1.12.dist-info/LICENSE
django_sssoon-0.1.12.dist-info/WHEEL
django_sssoon-0.1.12.dist-info/METADATA
django_sssoon-0.1.12.dist-info/RECORD
