Metadata-Version: 2.1
Name: django-sssoon
Version: 0.1.12
Summary: A simple Django app to add a beautiful coming soon page to your project.
Home-page: https://github.com/Kingpin-Apps/django-sssoon
Keywords: coming,soon,django,sssoon
Author: Hareem Adderley
Author-email: HADDERLEY@KINGPINAPPS.COM
Requires-Python: >=3.10,<4.0
Classifier: Programming Language :: Python :: 3
Classifier: Programming Language :: Python :: 3.10
Requires-Dist: Django
Requires-Dist: django-recaptcha (>=3.0.0,<4.0.0)
Project-URL: Repository, https://github.com/Kingpin-Apps/django-sssoon
